
{
    "affixes": [
        {
            "id": "affix_force",
            "ref": "Force",
            "type": "suffix",
            "portée": [1, 10],
            "échelonnage": "lin"
        },
        {
            "id": "affix_intel",
            "ref": "Intelligence",
            "type": "suffix",
            "portée": [1, 10],
            "échelonnage": "lin"
        },
        {
            "id": "affix_crit_chance",
            "ref": "CritPct",
            "type": "suffix",
            "portée": [1, 5],
            "échelonnage": "lin"
        },
        {
            "id": "affix_armor",
            "ref": "Armure",
            "type": "prefix",
            "portée": [5, 50],
            "échelonnage": "lin"
        }
    ]
}
